envreader/__init__.py
envreader/env_reader.py
envreader/exceptions.py
envreader/field.py
envreader/field_getter.py
envreader/version.py
envreader-1.0.0.dist-info/LICENSE
envreader-1.0.0.dist-info/METADATA
envreader-1.0.0.dist-info/WHEEL
envreader-1.0.0.dist-info/top_level.txt
envreader-1.0.0.dist-info/RECORD
